dev/__init__.py
dev/asgi.py
dev/settings.py
dev/urls.py
dev/wsgi.py
immunity_agent/__init__.py
immunity_agent/__main__.py
immunity_agent/config.py
immunity_agent/logger.py
immunity_agent/api/__init__.py
immunity_agent/api/client.py
immunity_agent/control_flow/__init__.py
immunity_agent/control_flow/control_flow.py
immunity_agent/middlewares/__init__.py
immunity_agent/middlewares/django_middleware.py
immunity_agent/middlewares/flask_middleware.py
immunity_agent/request/__init__.py
immunity_agent/request/django_request.py
immunity_agent/response/__init__.py
immunity_agent/response/django_response.py
immunity_iast-0.3.1.dist-info/METADATA
immunity_iast-0.3.1.dist-info/WHEEL
immunity_iast-0.3.1.dist-info/top_level.txt
immunity_iast-0.3.1.dist-info/RECORD
