Metadata-Version: 2.2
Name: immunity_iast
Version: 0.3.1
Summary: Python-агент Immunity IAST для интерактивного сканирования веб-приложений.
Author: l1ghth4t
Author-email: l1ghth4t <pirogov30002@gmail.com>
Classifier: Programming Language :: Python :: 3.11
Classifier: License :: OSI Approved :: MIT License
Classifier: Operating System :: OS Independent
Requires-Python: >=3.9
Dynamic: author
Dynamic: requires-python
